lares/__init__.py
lares/evaluate.py
lares/generate.py
lares/validate.py
lares-0.0.31.dist-info/LICENSE
lares-0.0.31.dist-info/METADATA
lares-0.0.31.dist-info/WHEEL
lares-0.0.31.dist-info/top_level.txt
lares-0.0.31.dist-info/RECORD
