Metadata-Version: 2.1
Name: lares
Version: 0.0.31
Summary: LARES: vaLidation, evAluation and REliability Solutions
Home-page: http://packages.python.org/lares
Author: Karime Maamari
Author-email: maamari@usc.edu
License: MIT
Keywords: evaluation,validation
Classifier: Programming Language :: Python :: 3.6
Classifier: Programming Language :: Python :: 3.7
Classifier: Programming Language :: Python :: 3.8
Classifier: Programming Language :: Python :: 3.9
Classifier: Programming Language :: Python :: 3.10
Classifier: Programming Language :: Python :: 3.11
Classifier: License :: OSI Approved :: MIT License
Requires-Python: >=3.6
License-File: LICENSE
Requires-Dist: openai (==0.27.8)
Requires-Dist: nltk (==3.7)
Requires-Dist: torch (==2.0.1)
Requires-Dist: transformers (==4.31.0)
Requires-Dist: rouge (==1.0.1)
Requires-Dist: bert-score (==0.3.12)
Requires-Dist: tqdm (==4.65.0)
Requires-Dist: fairlearn (==0.9.0)
Requires-Dist: datasets (==2.4.0)
